[
  {
    "word": "falcon",
    "syllables": [
      "fal",
      "con"
    ]
  },
  {
    "word": "glacier",
    "syllables": [
      "gla",
      "cier"
    ]
  },
  {
    "word": "horizon",
    "syllables": [
      "ho",
      "ri",
      "zon"
    ]
  },
  {
    "word": "ivy",
    "syllables": [
      "i",
      "vy"
    ]
  },
  {
    "word": "kernel",
    "syllables": [
      "ker",
      "nel"
    ]
  },
  {
    "word": "lantern",
    "syllables": [
      "lan",
      "tern"
    ]
  },
  {
    "word": "meadow",
    "syllables": [
      "mea",
      "dow"
    ]
  },
  {
    "word": "nectar",
    "syllables": [
      "nec",
      "tar"
    ]
  },
  {
    "word": "orbit",
    "syllables": [
      "or",
      "bit"
    ]
  },
  {
    "word": "quiver",
    "syllables": [
      "qui",
      "ver"
    ]
  },
  {
    "word": "velvet",
    "syllables": [
      "vel",
      "vet"
    ]
  },
  {
    "word": "xylo",
    "syllables": [
      "xy",
      "lo"
    ]
  },
  {
    "word": "ember",
    "syllables": [
      "em",
      "ber"
    ]
  },
  {
    "word": "inkwell",
    "syllables": [
      "ink",
      "well"
    ]
  },
  {
    "word": "jigsaw",
    "syllables": [
      "jig",
      "saw"
    ]
  },
  {
    "word": "tundra",
    "syllables": [
      "tun",
      "dra"
    ]
  },
  {
    "word": "underdog",
    "syllables": [
      "un",
      "der",
      "dog"
    ]
  },
  {
    "word": "vortex",
    "syllables": [
      "vor",
      "tex"
    ]
  },
  {
    "word": "wander",
    "syllables": [
      "wan",
      "der"
    ]
  },
  {
    "word": "compass",
    "syllables": [
      "com",
      "pass"
    ]
  },
  {
    "word": "envelope",
    "syllables": [
      "en",
      "ve",
      "lope"
    ]
  },
  {
    "word": "feather",
    "syllables": [
      "fea",
      "ther"
    ]
  },
  {
    "word": "goblet",
    "syllables": [
      "gob",
      "let"
    ]
  },
  {
    "word": "lantern",
    "syllables": [
      "lan",
      "tern"
    ]
  },
  {
    "word": "mushroom",
    "syllables": [
      "mush",
      "room"
    ]
  },
  {
    "word": "timber",
    "syllables": [
      "tim",
      "ber"
    ]
  },
  {
    "word": "whirlpool",
    "syllables": [
      "whirl",
      "pool"
    ]
  },
  {
    "word": "yodel",
    "syllables": [
      "yo",
      "del"
    ]
  },
  {
    "word": "zipper",
    "syllables": [
      "zip",
      "per"
    ]
  },
  {
    "word": "antler",
    "syllables": [
      "ant",
      "ler"
    ]
  },
  {
    "word": "elixir",
    "syllables": [
      "el",
      "ix",
      "ir"
    ]
  },
  {
    "word": "fossil",
    "syllables": [
      "fos",
      "sil"
    ]
  },
  {
    "word": "gravel",
    "syllables": [
      "gra",
      "vel"
    ]
  },
  {
    "word": "jester",
    "syllables": [
      "jes",
      "ter"
    ]
  },
  {
    "word": "nectarine",
    "syllables": [
      "nec",
      "ta",
      "rine"
    ]
  },
  {
    "word": "parchment",
    "syllables": [
      "parch",
      "ment"
    ]
  },
  {
    "word": "twilight",
    "syllables": [
      "twi",
      "light"
    ]
  },
  {
    "word": "uproot",
    "syllables": [
      "up",
      "root"
    ]
  },
  {
    "word": "wanderer",
    "syllables": [
      "wan",
      "der"
    ]
  },
  {
    "word": "zenith",
    "syllables": [
      "ze",
      "nith"
    ]
  }
]